ubii/__init__.py
ubii/topic_data_buffer.py
ubii/topic_data_proxy.py
ubii/ubii_client_node.py
ubii/ubii_network_client.py
ubii/ubii_service_client.py
ubii/ubii_topicdata_client.py
ubii_node_python_2-0.1.0.dist-info/LICENSE.txt
ubii_node_python_2-0.1.0.dist-info/METADATA
ubii_node_python_2-0.1.0.dist-info/WHEEL
ubii_node_python_2-0.1.0.dist-info/top_level.txt
ubii_node_python_2-0.1.0.dist-info/RECORD
