Metadata-Version: 2.2
Name: ubii-node-python-2
Version: 0.1.0
Summary: Python client node for Ubi-Interact
Author-email: Sandro Weber <sandro.weber@tum.de>, Anian Kalb <ge38tak@mytum.de>
Maintainer-email: Sandro Weber <sandro.weber@tum.de>
Project-URL: Repository, https://github.com/SandroWeber/ubii-node-python-v2
Project-URL: Issues, https://github.com/SandroWeber/ubii-node-python-v2/issues
Keywords: ubi-interact,ubii,MR,XR,context,publish-subscribe
Classifier: Development Status :: 4 - Beta
Classifier: Intended Audience :: Developers
Classifier: Topic :: Software Development :: Build Tools
Classifier: License :: OSI Approved :: MIT License
Classifier: Programming Language :: Python :: 3
Classifier: Programming Language :: Python :: 3.6
Classifier: Programming Language :: Python :: 3.7
Classifier: Programming Language :: Python :: 3.8
Classifier: Programming Language :: Python :: 3.9
Requires-Python: >=3.10
License-File: LICENSE.txt
Requires-Dist: ubii-msg-formats==0.16.7
Requires-Dist: aiohttp>=3.7.4
Requires-Dist: websockets>=11.0.3
Requires-Dist: Events>=0.5
